vid2txt/__init__.py
vid2txt/transcribe.py
vid2txt/version.py
vid2txt/vid2txt_cli.py
vid2txt/speech_to_text/__init__.py
vid2txt/speech_to_text/assemblyai.py
vid2txt/speech_to_text/base.py
vid2txt/utils/__init__.py
vid2txt/utils/formatter.py
vid2txt/utils/media.py
vid2txt/utils/summarizer.py
vid2txt/utils/translator.py
vid2txt/utils/templates/transcript_template.html
vid2txt-0.1.1.dist-info/licenses/LICENSE
vid2txt-0.1.1.dist-info/METADATA
vid2txt-0.1.1.dist-info/WHEEL
vid2txt-0.1.1.dist-info/entry_points.txt
vid2txt-0.1.1.dist-info/top_level.txt
vid2txt-0.1.1.dist-info/RECORD
