Metadata-Version: 2.4
Name: vid2txt
Version: 0.1.1
Summary: A Python package for transcribing videos to text using various speech-to-text services
Requires-Python: >=3.10
License-File: LICENSE
Requires-Dist: ffmpeg-python>=0.2.0
Requires-Dist: jinja2>=3.1.6
Requires-Dist: requests>=2.32.5
Requires-Dist: yt-dlp>=2023.12.30
Provides-Extra: dev
Requires-Dist: ipython; extra == "dev"
Requires-Dist: mypy; extra == "dev"
Requires-Dist: pre-commit; extra == "dev"
Requires-Dist: pytest; extra == "dev"
Requires-Dist: pytest-coverage; extra == "dev"
Requires-Dist: ruff; extra == "dev"
Dynamic: license-file
